pyweber/__init__.py
pyweber/admin/index.html
pyweber/admin/src/script.js
pyweber/admin/src/style.css
pyweber/cli/__init__.py
pyweber/cli/commands.py
pyweber/components/__init__.py
pyweber/components/form.py
pyweber/components/general.py
pyweber/components/input.py
pyweber/config/__init__.py
pyweber/config/config.py
pyweber/connection/__init__.py
pyweber/connection/http.py
pyweber/connection/reload.py
pyweber/connection/session.py
pyweber/connection/websocket.py
pyweber/core/__init__.py
pyweber/core/element.py
pyweber/core/events.py
pyweber/core/template.py
pyweber/core/window.py
pyweber/models/__init__.py
pyweber/models/cookies.py
pyweber/models/create_app.py
pyweber/models/element.py
pyweber/models/error_pages.py
pyweber/models/field.py
pyweber/models/field_storage.py
pyweber/models/file.py
pyweber/models/headers.py
pyweber/models/middleware.py
pyweber/models/openapi.py
pyweber/models/request.py
pyweber/models/response.py
pyweber/models/routes.py
pyweber/models/run.py
pyweber/models/task_manager.py
pyweber/models/template_diff.py
pyweber/models/ws_message.py
pyweber/pyweber/__init__.py
pyweber/pyweber/pyweber.py
pyweber/static/.gitignore
pyweber/static/config.toml
pyweber/static/css.css
pyweber/static/docs.html
pyweber/static/handlers.js
pyweber/static/html.html
pyweber/static/html401.html
pyweber/static/html404.html
pyweber/static/html500.html
pyweber/static/js.js
pyweber/static/loading.html
pyweber/static/main.py
pyweber/static/pyweber.css
pyweber/static/update.py
pyweber/static/favicon/android-chrome-192x192.png
pyweber/static/favicon/android-chrome-512x512.png
pyweber/static/favicon/apple-touch-icon.png
pyweber/static/favicon/favicon-16x16.png
pyweber/static/favicon/favicon-32x32.png
pyweber/static/favicon/favicon.ico
pyweber/static/favicon/pyweber.png
pyweber/static/favicon/site.webmanifest
pyweber/static/mdn-compact/css/at-rules/charset.json
pyweber/static/mdn-compact/css/at-rules/container.json
pyweber/static/mdn-compact/css/at-rules/counter-style.json
pyweber-1.0.1.dist-info/licenses/LICENSE
pyweber-1.0.1.dist-info/METADATA
pyweber-1.0.1.dist-info/WHEEL
pyweber-1.0.1.dist-info/entry_points.txt
pyweber-1.0.1.dist-info/top_level.txt
pyweber-1.0.1.dist-info/RECORD
