Metadata-Version: 2.4
Name: pyweber
Version: 1.0.1
Summary: A lightweight Python framework for building and managing web applications.
Author-email: DevPythonMZ <pypi.dev@gmail.com>
License-Expression: MIT
Project-URL: Documentation, https://pyweber.dev/
Project-URL: Source, https://github.com/pyweber/pyweber
Project-URL: Tracker, https://github.com/pyweber/pyweber/issues
Project-URL: PyPI, https://pypi.org/project/pyweber/
Project-URL: YouTube, https://youtube.com/@devpythonMZ
Project-URL: Examples, https://github.com/pyweber-examples
Requires-Python: >=3.10
License-File: LICENSE
Requires-Dist: websockets
Requires-Dist: watchdog
Requires-Dist: lxml
Requires-Dist: toml
Requires-Dist: questionary
Dynamic: license-file
